rpc_proxy
