Metadata-Version: 1.0
Name: tastypie-rpc-proxy
Version: 0.3.5
Summary: An extension of tastypie-queryset-client, designed intended for building RPC based on tastypie.
Home-page: http://github.com/nk113/tastypie-rpc-proxy/
Author: Nobu Kakegawa
Author-email: nobu@nk113.com
License: UNKNOWN
Platform: UNKNOWN
Classifier: Development Status :: 3 - Alpha
Classifier: Environment :: Web Environment
Classifier: Framework :: Django
Classifier: Intended Audience :: Developers
Classifier: License :: OSI Approved :: BSD License
Classifier: Operating System :: OS Independent
Classifier: Programming Language :: Python
Classifier: Topic :: Utilities
